MANIFEST.in
README.txt
development.ini
setup.cfg
setup.py
test.ini
SalvationFocus.egg-info/PKG-INFO
SalvationFocus.egg-info/SOURCES.txt
SalvationFocus.egg-info/dependency_links.txt
SalvationFocus.egg-info/entry_points.txt
SalvationFocus.egg-info/paste_deploy_config.ini_tmpl
SalvationFocus.egg-info/paster_plugins.txt
SalvationFocus.egg-info/requires.txt
SalvationFocus.egg-info/top_level.txt
dist/SalvationFocus-0.5-py2.5.egg
docs/index.txt
salvationfocus/__init__.py
salvationfocus/websetup.py
salvationfocus/config/__init__.py
salvationfocus/config/environment.py
salvationfocus/config/middleware.py
salvationfocus/config/routing.py
salvationfocus/controllers/__init__.py
salvationfocus/controllers/administrator.py
salvationfocus/controllers/believer.py
salvationfocus/controllers/error.py
salvationfocus/controllers/getprebeliever.py
salvationfocus/controllers/login.py
salvationfocus/controllers/main.py
salvationfocus/controllers/prebeliever.py
salvationfocus/controllers/submitter.py
salvationfocus/controllers/template.py
salvationfocus/lib/__init__.py
salvationfocus/lib/app_globals.py
salvationfocus/lib/base.py
salvationfocus/lib/helpers.py
salvationfocus/model/Administrator.py
salvationfocus/model/Believer.py
salvationfocus/model/Prebeliever.py
salvationfocus/model/Submitter.py
salvationfocus/model/__init__.py
salvationfocus/model/form.py
salvationfocus/public/sf.css
salvationfocus/templates/addadministrator.mako
salvationfocus/templates/addprebeliever.mako
salvationfocus/templates/addsubmitter.mako
salvationfocus/templates/adlist.mako
salvationfocus/templates/base.mako
salvationfocus/templates/bellist.mako
salvationfocus/templates/edit_email.mako
salvationfocus/templates/edit_password.mako
salvationfocus/templates/editprebeliever.mako
salvationfocus/templates/editsubmitter.mako
salvationfocus/templates/headerfooter.mako
salvationfocus/templates/list.mako
salvationfocus/templates/login.mako
salvationfocus/templates/main.mako
salvationfocus/templates/password.mako
salvationfocus/templates/prelist.mako
salvationfocus/templates/sublist.mako
salvationfocus/templates/util.mako
salvationfocus/tests/__init__.py
salvationfocus/tests/test_models.py
salvationfocus/tests/functional/__init__.py
salvationfocus/tests/functional/test_administrator.py
salvationfocus/tests/functional/test_believer.py
