Metadata-Version: 1.0
Name: SalvationFocus
Version: 0.5.1
Summary: Salvation Focus - Focusing your prayers on the lost.
Home-page: http://geekforgod.net
Author: Todd Johnson
Author-email: todd@geekforgod.net
License: UNKNOWN
Platform: UNKNOWN
